{"file":"MU-395.json","data":{"tipo":"MU","CM":"08","PR":"09","nombre":"Tubilla del Agua","censo":43,"escrutado_numero":68,"escrutado_porcentaje":36,"votantes_numero":17,"votantes_porcentaje":12,"abstencion_numero":22,"abstencion_porcentaje":90,"grupos":[["0002","F.A.C.",45,87,73],["0047","ImpulsoSocial",17,74,35],["0050","ALTER",80,24,6],["0053","VOX",80,26,53],["0038","PARTIDO ANDALUCISTA",58,33,29],["0186","DISCAPACITADOS Y ENFERMEDADES RARAS",45,30,62],["0039","D.N.",58,28,31],["00","Blanco",63,73,47],["00","Nulos",49,69,7]]},"children":[],"parent":{"id":"09","nombre":"Burgos","json":"PR-09.json"}}