{"file":"MU-369.json","data":{"tipo":"MU","CM":"08","PR":"37","nombre":"Villaseco de los Gamitos","censo":82,"escrutado_numero":12,"escrutado_porcentaje":47,"votantes_numero":46,"votantes_porcentaje":61,"abstencion_numero":51,"abstencion_porcentaje":14,"grupos":[["0002","F.A.C.",49,4,69],["0047","ImpulsoSocial",97,78,100],["0050","ALTER",49,99,66],["0053","VOX",9,52,32],["0038","PARTIDO ANDALUCISTA",70,44,43],["0186","DISCAPACITADOS Y ENFERMEDADES RARAS",52,39,43],["0039","D.N.",56,7,96],["00","Blanco",89,98,78],["00","Nulos",5,64,3]]},"children":[],"parent":{"id":"37","nombre":"Salamanca","json":"PR-37.json"}}