{"file":"MU-445.json","data":{"tipo":"MU","CM":"08","PR":"09","nombre":"Villambistia","censo":82,"escrutado_numero":4,"escrutado_porcentaje":9,"votantes_numero":61,"votantes_porcentaje":97,"abstencion_numero":60,"abstencion_porcentaje":16,"grupos":[["0002","F.A.C.",93,51,56],["0047","ImpulsoSocial",65,62,43],["0050","ALTER",91,43,50],["0053","VOX",69,50,25],["0038","PARTIDO ANDALUCISTA",65,55,93],["0186","DISCAPACITADOS Y ENFERMEDADES RARAS",78,87,84],["0039","D.N.",40,15,98],["00","Blanco",90,84,17],["00","Nulos",53,91,26]]},"children":[],"parent":{"id":"09","nombre":"Burgos","json":"PR-09.json"}}