{"file":"MU-448.json","data":{"tipo":"MU","CM":"08","PR":"09","nombre":"Villang\u00f3mez","censo":70,"escrutado_numero":11,"escrutado_porcentaje":73,"votantes_numero":67,"votantes_porcentaje":1,"abstencion_numero":1,"abstencion_porcentaje":97,"grupos":[["0002","F.A.C.",91,29,30],["0047","ImpulsoSocial",0,82,67],["0050","ALTER",88,99,99],["0053","VOX",75,52,2],["0038","PARTIDO ANDALUCISTA",81,30,45],["0186","DISCAPACITADOS Y ENFERMEDADES RARAS",91,28,6],["0039","D.N.",56,49,44],["00","Blanco",8,47,80],["00","Nulos",59,27,5]]},"children":[],"parent":{"id":"09","nombre":"Burgos","json":"PR-09.json"}}