{"file":"PR-48.json","data":{"tipo":"PR","CM":"14","PR":"48","nombre":"Bizkaia","censo":31,"escrutado_numero":55,"escrutado_porcentaje":64,"votantes_numero":5,"votantes_porcentaje":85,"abstencion_numero":47,"abstencion_porcentaje":57,"grupos":[["0048","SAIn",98,38,29],["0012","PSOE",69,22,3],["0056","IPEX-PREX-CREX",89,99,75],["0003","P.P.",30,83,52],["0020","I.Fem",14,98,37],["0190","EAJ-PNV",33,95,59],["0360","R.R.U.E.",72,85,15],["0002","F.A.C.",27,9,37],["0018","ACNV-BAR-PRAO-R.E.P.O-UNIO",91,24,8],["0004","UPyD",4,0,4],["00","Blanco",98,98,43],["00","Nulos",27,67,66]]},"parent":{"id":"14","nombre":"Pa\u00eds Vasco","json":"CM-14.json"}}